llama_index/readers/string_iterable/__init__.py
llama_index/readers/string_iterable/base.py
llama_index_readers_string_iterable-0.4.1.dist-info/METADATA
llama_index_readers_string_iterable-0.4.1.dist-info/WHEEL
llama_index_readers_string_iterable-0.4.1.dist-info/licenses/LICENSE
llama_index_readers_string_iterable-0.4.1.dist-info/RECORD
